immutable_default_args/compatibility.py
immutable_default_args/main.py
immutable_default_args/__init__.py
immutable_default_args-0.0.9.dist-info/DESCRIPTION.rst
immutable_default_args-0.0.9.dist-info/METADATA
immutable_default_args-0.0.9.dist-info/metadata.json
immutable_default_args-0.0.9.dist-info/RECORD
immutable_default_args-0.0.9.dist-info/top_level.txt
immutable_default_args-0.0.9.dist-info/WHEEL
