Metadata-Version: 2.0
Name: immutable-default-args
Version: 0.0.9
Summary: Very small package to automatically safeguard mutable function arguments, preventing them from being modified.
Home-page: http://timmwagener.com/
Author: Timm Wagener
Author-email: wagenertimm@gmail.com
License: MIT
Platform: UNKNOWN
Classifier: Development Status :: 3 - Alpha
Classifier: Intended Audience :: Developers
Classifier: License :: OSI Approved :: MIT License
Classifier: Natural Language :: English
Classifier: Programming Language :: Python :: 2
Classifier: Programming Language :: Python :: 2.7
Classifier: Programming Language :: Python :: 3
Classifier: Programming Language :: Python :: 3.3
Classifier: Programming Language :: Python :: 3.4
Classifier: Programming Language :: Python :: 3.5
